{
    "data": [
        {
            "id": "1130796030374690_1154543184666641",
            "message": "// FREE DONUTS // TONITE!\n\n***Last The Girlfriend Society party at Sorry Grandma! before we make our move to our new home around the corner***\n\nWe gots da Jam. We gots da Original. We gots da Chocolate. Get ya free donuts - first 100 people through the doors tonight from 11PM. \n\nThe Girlfriend Society / / G L A Z ED & C O N F U S E D / /",
            "updated_time": "2016-12-17T05:08:21+0000"
        },
        {
            "id": "1130796030374690_1138558466265113",
            "message": "F R E E // D O N U T S // B4 MIDN1TE\n\nCome get Glazed & Confused with us. \n\nR+B // Hip Hop // Twerk // 2 Floors\n\n// The Girlfriend Society",
            "updated_time": "2016-12-11T21:37:17+0000"
        }
    ],
    "paging": {
        "next": "https://graph.facebook.com/v2.8/1130796030374690/feed?access_token=190441714759199|QdoMmLvHYEUzSeeLyPK4Awg6Zv4&limit=25&until=1481492237&__paging_token=enc_AdBaWh2mrMKvRoyZBJuOEbomHIaif9mO0JWNATZAfUwkaN9opLjUFKEE1LqKYCIIn0rAW6iuX36syGVNU2Oi3Nl94o2zLSJr8rHljqKVF9omAPOQZDZD",
        "previous": "https://graph.facebook.com/v2.8/1130796030374690/feed?since=1481951301&access_token=190441714759199|QdoMmLvHYEUzSeeLyPK4Awg6Zv4&limit=25&__paging_token=enc_AdBJQIbmlvFgKgZCKNZBN4DH7wWZBaN8oXZBZCGGErmTdLd2RE1FM9snDClTXi9VcbVfV8YoksSadminw1NU9gjZBqU4Fuc1RXqqjTOfdhV4ATskn1zgZDZD&__previous=1"
    }
}