{
    "data": [
        {
            "id": "1861784927373684_1870359026516274",
            "message": "\u65b0\u52a0\uff1a\u795e\u5b78\u751f\u53ef\u4eab\u6709\u7279\u5225\u512a\u60e0: $80\u4e00\u5802 (\u58314\u58028\u6298\u512a\u60e0\u5373 $256 )\u3002\n\n\u8cbb\u7528\uff1a\u4e00\u5802$120/\u4f4d (\u58314\u58028\u6298\u512a\u60e0\u5373$384 )\u3002\u53e6\u5916\uff0c18-35\u6b72\u7684\u53c3\u52a0\u8005\u53ca\u795e\u5b78\u751f\u53ef\u4eab\u6709\u7279\u5225\u512a\u60e0: $80\u4e00\u5802 (\u58314\u58028\u6298\u512a\u60e0\u5373 $256 )\u3002",
            "updated_time": "2016-12-15T02:52:31+0000"
        },
        {
            "id": "1861784927373684_1861859397366237",
            "message": "\u597d\u8fd1\u6211\u558e\uff01\ud83d\ude2e1\u5206\u9418\u8def\u7a0b",
            "updated_time": "2016-11-28T10:18:27+0000"
        }
    ],
    "paging": {
        "next": "https://graph.facebook.com/v2.8/1861784927373684/feed?access_token=190441714759199|QdoMmLvHYEUzSeeLyPK4Awg6Zv4&limit=25&until=1480328307&__paging_token=enc_AdD3O9XOy7obEXg9PLQ4Bf4ZC1BpFNkzHT6ZBnbfBJd0DgvnrojZAwYOiXVUqPFFcLrQ2PP9ZBADWyZBtceOOvDV0J7cfan0fTzhDmWPVV1UcknxYjgZDZD",
        "previous": "https://graph.facebook.com/v2.8/1861784927373684/feed?since=1481770351&access_token=190441714759199|QdoMmLvHYEUzSeeLyPK4Awg6Zv4&limit=25&__paging_token=enc_AdCRrs2v9tOy0SXKZBuSslPhrJo5thxOPIacPd19k6uA6aD4ZBe9PppJ0Q5NoYEjEIpzPeRcsZAnXh3M7qVSlVgZBUkt9tAEiTCiEkQmljMoDQxlNAZDZD&__previous=1"
    }
}