{
    "data": [
        {
            "id": "268587053508790_347048748995953",
            "message": "\u771f\u60f3\u53bb\u5462\uff01",
            "updated_time": "2016-11-14T00:17:18+0000"
        },
        {
            "id": "268587053508790_268587056842123",
            "story": "Gaia Philharmonic Choir added an event.",
            "updated_time": "2016-06-29T11:41:35+0000"
        }
    ],
    "paging": {
        "next": "https://graph.facebook.com/v2.8/268587053508790/feed?access_token=190441714759199|QdoMmLvHYEUzSeeLyPK4Awg6Zv4&limit=25&until=1467200495&__paging_token=enc_AdD0bGu8apZCZAbqy969NDzhYu0BYFnNKCzfrzxhl8oopOXMChkppeaTx7WRqpxGHaooOxWAfEmLTs5j83QkldSWNw7RwZC0UhK9FYGfiNZChzkv5gZDZD",
        "previous": "https://graph.facebook.com/v2.8/268587053508790/feed?since=1479082638&access_token=190441714759199|QdoMmLvHYEUzSeeLyPK4Awg6Zv4&limit=25&__paging_token=enc_AdAcPgKRZBZCP7GUD9PEyapEHPyLjKGCE4VAMRT66eHNobvdUsNz669m1rgZCDYj71KIVZCNZBNMVTo2LdTescMZBF8XPnX7BMkb1dJv9udDLVVXwKWAZDZD&__previous=1"
    }
}