{
    "data": [
        {
            "id": "336088353443639_339216679797473",
            "message": "\u5373\u5c07\u65bc12\u670824\u65e5\u958b\u5c55\u7684\u3008\u610f\u8b58\u5c0d\u8a71\u3009\uff0c\u9996\u64ad\u9810\u544a\u5e36\u9818\u5927\u5bb6\u89c0\u770b\u840c\u767c\u82ae\u6dc7\u6f5b\u610f\u8b58\u7684\u5168\u7a0b\u8def\u5f91\uff0c\u756b\u9762\u5f14\u8a6d\u5982\u5922\u3001\u6e05\u6670\u5982\u73fe\u5be6\uff0c\u93e1\u982d\u4e0b\u7684\u758a\u5f71\uff0c\u6210\u70ba\u601d\u7dd2\u7684\u5c0d\u8a71\u3002\n\n#\u5b8c\u6574\u5275\u4f5c\u65bc\u958b\u5e55\u7576\u65e5\u9996\u6620\n#\u610f\u8b58\u5c0d\u8a71\n#\u807d\u5f97\u51fa\u4f86\u7247\u5c3e\u8b1b\u4ec0\u9ebc\u55ce",
            "updated_time": "2016-12-04T15:24:00+0000"
        }
    ],
    "paging": {
        "next": "https://graph.facebook.com/v2.8/336088353443639/feed?access_token=190441714759199|QdoMmLvHYEUzSeeLyPK4Awg6Zv4&limit=25&until=1480865040&__paging_token=enc_AdCQEhNi1RtZBydkiZCDvpWbO7wAyel0TaVD2tu48InWMxUQm8ZCHNgOkAJeLEQ5DCGbWLACCIXhQbyZAL0V1pv9vZAXAOrtYdlk0kUuCFDXZCuREf4gZDZD",
        "previous": "https://graph.facebook.com/v2.8/336088353443639/feed?since=1480865040&access_token=190441714759199|QdoMmLvHYEUzSeeLyPK4Awg6Zv4&limit=25&__paging_token=enc_AdCQEhNi1RtZBydkiZCDvpWbO7wAyel0TaVD2tu48InWMxUQm8ZCHNgOkAJeLEQ5DCGbWLACCIXhQbyZAL0V1pv9vZAXAOrtYdlk0kUuCFDXZCuREf4gZDZD&__previous=1"
    }
}